{"nodes": [{"id": "d_work_datastore_archives_100ask_lvgl_docs_docs_config_builder_py", "label": "config_builder.py", "file_type": "code", "source_file": "D:\\work\\datastore\\archives\\100ask_lvgl_docs\\docs\\config_builder.py", "source_location": "L1"}, {"id": "docs_config_builder_run", "label": "run()", "file_type": "code", "source_file": "D:\\work\\datastore\\archives\\100ask_lvgl_docs\\docs\\config_builder.py", "source_location": "L21"}, {"id": "docs_config_builder_cleanup", "label": "cleanup()", "file_type": "code", "source_file": "D:\\work\\datastore\\archives\\100ask_lvgl_docs\\docs\\config_builder.py", "source_location": "L55"}, {"id": "docs_config_builder_rationale_1", "label": "Create lv_conf.h in same directory as this file from ../lv_conf_template.h that", "file_type": "rationale", "source_file": "D:\\work\\datastore\\archives\\100ask_lvgl_docs\\docs\\config_builder.py", "source_location": "L1"}], "edges": [{"source": "d_work_datastore_archives_100ask_lvgl_docs_docs_config_builder_py", "target": "os", "relation": "imports", "confidence": "EXTRACTED", "source_file": "D:\\work\\datastore\\archives\\100ask_lvgl_docs\\docs\\config_builder.py", "source_location": "L10", "weight": 1.0}, {"source": "d_work_datastore_archives_100ask_lvgl_docs_docs_config_builder_py", "target": "docs_config_builder_run", "relation": "contains", "confidence": "EXTRACTED", "source_file": "D:\\work\\datastore\\archives\\100ask_lvgl_docs\\docs\\config_builder.py", "source_location": "L21", "weight": 1.0}, {"source": "d_work_datastore_archives_100ask_lvgl_docs_docs_config_builder_py", "target": "docs_config_builder_cleanup", "relation": "contains", "confidence": "EXTRACTED", "source_file": "D:\\work\\datastore\\archives\\100ask_lvgl_docs\\docs\\config_builder.py", "source_location": "L55", "weight": 1.0}, {"source": "docs_config_builder_rationale_1", "target": "d_work_datastore_archives_100ask_lvgl_docs_docs_config_builder_py", "relation": "rationale_for", "confidence": "EXTRACTED", "source_file": "D:\\work\\datastore\\archives\\100ask_lvgl_docs\\docs\\config_builder.py", "source_location": "L1", "weight": 1.0}], "raw_calls": [{"caller_nid": "docs_config_builder_run", "callee": "open", "is_member_call": false, "source_file": "D:\\work\\datastore\\archives\\100ask_lvgl_docs\\docs\\config_builder.py", "source_location": "L27"}, {"caller_nid": "docs_config_builder_run", "callee": "read", "is_member_call": true, "source_file": "D:\\work\\datastore\\archives\\100ask_lvgl_docs\\docs\\config_builder.py", "source_location": "L28"}, {"caller_nid": "docs_config_builder_run", "callee": "split", "is_member_call": true, "source_file": "D:\\work\\datastore\\archives\\100ask_lvgl_docs\\docs\\config_builder.py", "source_location": "L30"}, {"caller_nid": "docs_config_builder_run", "callee": "enumerate", "is_member_call": false, "source_file": "D:\\work\\datastore\\archives\\100ask_lvgl_docs\\docs\\config_builder.py", "source_location": "L32"}, {"caller_nid": "docs_config_builder_run", "callee": "split", "is_member_call": true, "source_file": "D:\\work\\datastore\\archives\\100ask_lvgl_docs\\docs\\config_builder.py", "source_location": "L37"}, {"caller_nid": "docs_config_builder_run", "callee": "enumerate", "is_member_call": false, "source_file": "D:\\work\\datastore\\archives\\100ask_lvgl_docs\\docs\\config_builder.py", "source_location": "L39"}, {"caller_nid": "docs_config_builder_run", "callee": "join", "is_member_call": true, "source_file": "D:\\work\\datastore\\archives\\100ask_lvgl_docs\\docs\\config_builder.py", "source_location": "L43"}, {"caller_nid": "docs_config_builder_run", "callee": "startswith", "is_member_call": true, "source_file": "D:\\work\\datastore\\archives\\100ask_lvgl_docs\\docs\\config_builder.py", "source_location": "L45"}, {"caller_nid": "docs_config_builder_run", "callee": "replace", "is_member_call": true, "source_file": "D:\\work\\datastore\\archives\\100ask_lvgl_docs\\docs\\config_builder.py", "source_location": "L46"}, {"caller_nid": "docs_config_builder_run", "callee": "join", "is_member_call": true, "source_file": "D:\\work\\datastore\\archives\\100ask_lvgl_docs\\docs\\config_builder.py", "source_location": "L49"}, {"caller_nid": "docs_config_builder_run", "callee": "open", "is_member_call": false, "source_file": "D:\\work\\datastore\\archives\\100ask_lvgl_docs\\docs\\config_builder.py", "source_location": "L51"}, {"caller_nid": "docs_config_builder_run", "callee": "write", "is_member_call": true, "source_file": "D:\\work\\datastore\\archives\\100ask_lvgl_docs\\docs\\config_builder.py", "source_location": "L52"}, {"caller_nid": "docs_config_builder_cleanup", "callee": "exists", "is_member_call": true, "source_file": "D:\\work\\datastore\\archives\\100ask_lvgl_docs\\docs\\config_builder.py", "source_location": "L56"}, {"caller_nid": "docs_config_builder_cleanup", "callee": "remove", "is_member_call": true, "source_file": "D:\\work\\datastore\\archives\\100ask_lvgl_docs\\docs\\config_builder.py", "source_location": "L57"}]}