{"nodes": [{"id": "d_work_datastore_archives_100ask_lvgl_docs_examples_anim_lv_example_anim_1_c", "label": "lv_example_anim_1.c", "file_type": "code", "source_file": "D:\\work\\datastore\\archives\\100ask_lvgl_docs\\examples\\anim\\lv_example_anim_1.c", "source_location": "L1"}, {"id": "anim_lv_example_anim_1_anim_x_cb", "label": "anim_x_cb()", "file_type": "code", "source_file": "D:\\work\\datastore\\archives\\100ask_lvgl_docs\\examples\\anim\\lv_example_anim_1.c", "source_location": "L4"}, {"id": "anim_lv_example_anim_1_sw_event_cb", "label": "sw_event_cb()", "file_type": "code", "source_file": "D:\\work\\datastore\\archives\\100ask_lvgl_docs\\examples\\anim\\lv_example_anim_1.c", "source_location": "L9"}, {"id": "anim_lv_example_anim_1_lv_example_anim_1", "label": "lv_example_anim_1()", "file_type": "code", "source_file": "D:\\work\\datastore\\archives\\100ask_lvgl_docs\\examples\\anim\\lv_example_anim_1.c", "source_location": "L40"}], "edges": [{"source": "d_work_datastore_archives_100ask_lvgl_docs_examples_anim_lv_example_anim_1_c", "target": "lv_examples", "relation": "imports", "confidence": "EXTRACTED", "source_file": "D:\\work\\datastore\\archives\\100ask_lvgl_docs\\examples\\anim\\lv_example_anim_1.c", "source_location": "L1", "weight": 1.0}, {"source": "d_work_datastore_archives_100ask_lvgl_docs_examples_anim_lv_example_anim_1_c", "target": "anim_lv_example_anim_1_anim_x_cb", "relation": "contains", "confidence": "EXTRACTED", "source_file": "D:\\work\\datastore\\archives\\100ask_lvgl_docs\\examples\\anim\\lv_example_anim_1.c", "source_location": "L4", "weight": 1.0}, {"source": "d_work_datastore_archives_100ask_lvgl_docs_examples_anim_lv_example_anim_1_c", "target": "anim_lv_example_anim_1_sw_event_cb", "relation": "contains", "confidence": "EXTRACTED", "source_file": "D:\\work\\datastore\\archives\\100ask_lvgl_docs\\examples\\anim\\lv_example_anim_1.c", "source_location": "L9", "weight": 1.0}, {"source": "d_work_datastore_archives_100ask_lvgl_docs_examples_anim_lv_example_anim_1_c", "target": "anim_lv_example_anim_1_lv_example_anim_1", "relation": "contains", "confidence": "EXTRACTED", "source_file": "D:\\work\\datastore\\archives\\100ask_lvgl_docs\\examples\\anim\\lv_example_anim_1.c", "source_location": "L40", "weight": 1.0}], "raw_calls": [{"caller_nid": "anim_lv_example_anim_1_anim_x_cb", "callee": "lv_obj_set_x", "is_member_call": false, "source_file": "D:\\work\\datastore\\archives\\100ask_lvgl_docs\\examples\\anim\\lv_example_anim_1.c", "source_location": "L6"}, {"caller_nid": "anim_lv_example_anim_1_sw_event_cb", "callee": "lv_event_get_target", "is_member_call": false, "source_file": "D:\\work\\datastore\\archives\\100ask_lvgl_docs\\examples\\anim\\lv_example_anim_1.c", "source_location": "L11"}, {"caller_nid": "anim_lv_example_anim_1_sw_event_cb", "callee": "lv_event_get_user_data", "is_member_call": false, "source_file": "D:\\work\\datastore\\archives\\100ask_lvgl_docs\\examples\\anim\\lv_example_anim_1.c", "source_location": "L12"}, {"caller_nid": "anim_lv_example_anim_1_sw_event_cb", "callee": "lv_obj_has_state", "is_member_call": false, "source_file": "D:\\work\\datastore\\archives\\100ask_lvgl_docs\\examples\\anim\\lv_example_anim_1.c", "source_location": "L14"}, {"caller_nid": "anim_lv_example_anim_1_sw_event_cb", "callee": "lv_anim_init", "is_member_call": false, "source_file": "D:\\work\\datastore\\archives\\100ask_lvgl_docs\\examples\\anim\\lv_example_anim_1.c", "source_location": "L16"}, {"caller_nid": "anim_lv_example_anim_1_sw_event_cb", "callee": "lv_anim_set_var", "is_member_call": false, "source_file": "D:\\work\\datastore\\archives\\100ask_lvgl_docs\\examples\\anim\\lv_example_anim_1.c", "source_location": "L17"}, {"caller_nid": "anim_lv_example_anim_1_sw_event_cb", "callee": "lv_anim_set_values", "is_member_call": false, "source_file": "D:\\work\\datastore\\archives\\100ask_lvgl_docs\\examples\\anim\\lv_example_anim_1.c", "source_location": "L18"}, {"caller_nid": "anim_lv_example_anim_1_sw_event_cb", "callee": "lv_obj_get_x", "is_member_call": false, "source_file": "D:\\work\\datastore\\archives\\100ask_lvgl_docs\\examples\\anim\\lv_example_anim_1.c", "source_location": "L18"}, {"caller_nid": "anim_lv_example_anim_1_sw_event_cb", "callee": "lv_anim_set_duration", "is_member_call": false, "source_file": "D:\\work\\datastore\\archives\\100ask_lvgl_docs\\examples\\anim\\lv_example_anim_1.c", "source_location": "L19"}, {"caller_nid": "anim_lv_example_anim_1_sw_event_cb", "callee": "lv_anim_set_exec_cb", "is_member_call": false, "source_file": "D:\\work\\datastore\\archives\\100ask_lvgl_docs\\examples\\anim\\lv_example_anim_1.c", "source_location": "L20"}, {"caller_nid": "anim_lv_example_anim_1_sw_event_cb", "callee": "lv_anim_set_path_cb", "is_member_call": false, "source_file": "D:\\work\\datastore\\archives\\100ask_lvgl_docs\\examples\\anim\\lv_example_anim_1.c", "source_location": "L21"}, {"caller_nid": "anim_lv_example_anim_1_sw_event_cb", "callee": "lv_anim_start", "is_member_call": false, "source_file": "D:\\work\\datastore\\archives\\100ask_lvgl_docs\\examples\\anim\\lv_example_anim_1.c", "source_location": "L22"}, {"caller_nid": "anim_lv_example_anim_1_sw_event_cb", "callee": "lv_anim_init", "is_member_call": false, "source_file": "D:\\work\\datastore\\archives\\100ask_lvgl_docs\\examples\\anim\\lv_example_anim_1.c", "source_location": "L26"}, {"caller_nid": "anim_lv_example_anim_1_sw_event_cb", "callee": "lv_anim_set_var", "is_member_call": false, "source_file": "D:\\work\\datastore\\archives\\100ask_lvgl_docs\\examples\\anim\\lv_example_anim_1.c", "source_location": "L27"}, {"caller_nid": "anim_lv_example_anim_1_sw_event_cb", "callee": "lv_anim_set_values", "is_member_call": false, "source_file": "D:\\work\\datastore\\archives\\100ask_lvgl_docs\\examples\\anim\\lv_example_anim_1.c", "source_location": "L28"}, {"caller_nid": "anim_lv_example_anim_1_sw_event_cb", "callee": "lv_obj_get_x", "is_member_call": false, "source_file": "D:\\work\\datastore\\archives\\100ask_lvgl_docs\\examples\\anim\\lv_example_anim_1.c", "source_location": "L28"}, {"caller_nid": "anim_lv_example_anim_1_sw_event_cb", "callee": "lv_obj_get_width", "is_member_call": false, "source_file": "D:\\work\\datastore\\archives\\100ask_lvgl_docs\\examples\\anim\\lv_example_anim_1.c", "source_location": "L28"}, {"caller_nid": "anim_lv_example_anim_1_sw_event_cb", "callee": "lv_anim_set_duration", "is_member_call": false, "source_file": "D:\\work\\datastore\\archives\\100ask_lvgl_docs\\examples\\anim\\lv_example_anim_1.c", "source_location": "L29"}, {"caller_nid": "anim_lv_example_anim_1_sw_event_cb", "callee": "lv_anim_set_exec_cb", "is_member_call": false, "source_file": "D:\\work\\datastore\\archives\\100ask_lvgl_docs\\examples\\anim\\lv_example_anim_1.c", "source_location": "L30"}, {"caller_nid": "anim_lv_example_anim_1_sw_event_cb", "callee": "lv_anim_set_path_cb", "is_member_call": false, "source_file": "D:\\work\\datastore\\archives\\100ask_lvgl_docs\\examples\\anim\\lv_example_anim_1.c", "source_location": "L31"}, {"caller_nid": "anim_lv_example_anim_1_sw_event_cb", "callee": "lv_anim_start", "is_member_call": false, "source_file": "D:\\work\\datastore\\archives\\100ask_lvgl_docs\\examples\\anim\\lv_example_anim_1.c", "source_location": "L32"}, {"caller_nid": "anim_lv_example_anim_1_lv_example_anim_1", "callee": "lv_label_create", "is_member_call": false, "source_file": "D:\\work\\datastore\\archives\\100ask_lvgl_docs\\examples\\anim\\lv_example_anim_1.c", "source_location": "L42"}, {"caller_nid": "anim_lv_example_anim_1_lv_example_anim_1", "callee": "lv_screen_active", "is_member_call": false, "source_file": "D:\\work\\datastore\\archives\\100ask_lvgl_docs\\examples\\anim\\lv_example_anim_1.c", "source_location": "L42"}, {"caller_nid": "anim_lv_example_anim_1_lv_example_anim_1", "callee": "lv_label_set_text", "is_member_call": false, "source_file": "D:\\work\\datastore\\archives\\100ask_lvgl_docs\\examples\\anim\\lv_example_anim_1.c", "source_location": "L43"}, {"caller_nid": "anim_lv_example_anim_1_lv_example_anim_1", "callee": "lv_obj_set_pos", "is_member_call": false, "source_file": "D:\\work\\datastore\\archives\\100ask_lvgl_docs\\examples\\anim\\lv_example_anim_1.c", "source_location": "L44"}, {"caller_nid": "anim_lv_example_anim_1_lv_example_anim_1", "callee": "lv_switch_create", "is_member_call": false, "source_file": "D:\\work\\datastore\\archives\\100ask_lvgl_docs\\examples\\anim\\lv_example_anim_1.c", "source_location": "L46"}, {"caller_nid": "anim_lv_example_anim_1_lv_example_anim_1", "callee": "lv_screen_active", "is_member_call": false, "source_file": "D:\\work\\datastore\\archives\\100ask_lvgl_docs\\examples\\anim\\lv_example_anim_1.c", "source_location": "L46"}, {"caller_nid": "anim_lv_example_anim_1_lv_example_anim_1", "callee": "lv_obj_center", "is_member_call": false, "source_file": "D:\\work\\datastore\\archives\\100ask_lvgl_docs\\examples\\anim\\lv_example_anim_1.c", "source_location": "L47"}, {"caller_nid": "anim_lv_example_anim_1_lv_example_anim_1", "callee": "lv_obj_add_state", "is_member_call": false, "source_file": "D:\\work\\datastore\\archives\\100ask_lvgl_docs\\examples\\anim\\lv_example_anim_1.c", "source_location": "L48"}, {"caller_nid": "anim_lv_example_anim_1_lv_example_anim_1", "callee": "lv_obj_add_event_cb", "is_member_call": false, "source_file": "D:\\work\\datastore\\archives\\100ask_lvgl_docs\\examples\\anim\\lv_example_anim_1.c", "source_location": "L49"}]}