{"nodes": [{"id": "d_work_datastore_archives_100ask_lvgl_docs_src_misc_lv_area_h", "label": "lv_area.h", "file_type": "code", "source_file": "D:\\work\\datastore\\archives\\100ask_lvgl_docs\\src\\misc\\lv_area.h", "source_location": "L1"}, {"id": "misc_lv_area_lv_area_copy", "label": "lv_area_copy()", "file_type": "code", "source_file": "D:\\work\\datastore\\archives\\100ask_lvgl_docs\\src\\misc\\lv_area.h", "source_location": "L107"}], "edges": [{"source": "d_work_datastore_archives_100ask_lvgl_docs_src_misc_lv_area_h", "target": "lv_conf_internal", "relation": "imports", "confidence": "EXTRACTED", "source_file": "D:\\work\\datastore\\archives\\100ask_lvgl_docs\\src\\misc\\lv_area.h", "source_location": "L16", "weight": 1.0}, {"source": "d_work_datastore_archives_100ask_lvgl_docs_src_misc_lv_area_h", "target": "lv_types", "relation": "imports", "confidence": "EXTRACTED", "source_file": "D:\\work\\datastore\\archives\\100ask_lvgl_docs\\src\\misc\\lv_area.h", "source_location": "L17", "weight": 1.0}, {"source": "d_work_datastore_archives_100ask_lvgl_docs_src_misc_lv_area_h", "target": "lv_math", "relation": "imports", "confidence": "EXTRACTED", "source_file": "D:\\work\\datastore\\archives\\100ask_lvgl_docs\\src\\misc\\lv_area.h", "source_location": "L18", "weight": 1.0}, {"source": "d_work_datastore_archives_100ask_lvgl_docs_src_misc_lv_area_h", "target": "misc_lv_area_lv_area_copy", "relation": "contains", "confidence": "EXTRACTED", "source_file": "D:\\work\\datastore\\archives\\100ask_lvgl_docs\\src\\misc\\lv_area.h", "source_location": "L107", "weight": 1.0}], "raw_calls": []}