{"nodes": [{"id": "d_work_datastore_archives_100ask_lvgl_docs_src_draw_nema_gfx_lv_draw_nema_gfx_stm32_hal_c", "label": "lv_draw_nema_gfx_stm32_hal.c", "file_type": "code", "source_file": "D:\\work\\datastore\\archives\\100ask_lvgl_docs\\src\\draw\\nema_gfx\\lv_draw_nema_gfx_stm32_hal.c", "source_location": "L1"}, {"id": "nema_gfx_lv_draw_nema_gfx_stm32_hal_hal_gpu2d_commandlistcpltcallback", "label": "HAL_GPU2D_CommandListCpltCallback()", "file_type": "code", "source_file": "D:\\work\\datastore\\archives\\100ask_lvgl_docs\\src\\draw\\nema_gfx\\lv_draw_nema_gfx_stm32_hal.c", "source_location": "L85"}, {"id": "nema_gfx_lv_draw_nema_gfx_stm32_hal_nema_sys_init", "label": "nema_sys_init()", "file_type": "code", "source_file": "D:\\work\\datastore\\archives\\100ask_lvgl_docs\\src\\draw\\nema_gfx\\lv_draw_nema_gfx_stm32_hal.c", "source_location": "L96"}, {"id": "nema_gfx_lv_draw_nema_gfx_stm32_hal_nema_reg_read", "label": "nema_reg_read()", "file_type": "code", "source_file": "D:\\work\\datastore\\archives\\100ask_lvgl_docs\\src\\draw\\nema_gfx\\lv_draw_nema_gfx_stm32_hal.c", "source_location": "L131"}, {"id": "nema_gfx_lv_draw_nema_gfx_stm32_hal_nema_reg_write", "label": "nema_reg_write()", "file_type": "code", "source_file": "D:\\work\\datastore\\archives\\100ask_lvgl_docs\\src\\draw\\nema_gfx\\lv_draw_nema_gfx_stm32_hal.c", "source_location": "L136"}, {"id": "nema_gfx_lv_draw_nema_gfx_stm32_hal_nema_wait_irq", "label": "nema_wait_irq()", "file_type": "code", "source_file": "D:\\work\\datastore\\archives\\100ask_lvgl_docs\\src\\draw\\nema_gfx\\lv_draw_nema_gfx_stm32_hal.c", "source_location": "L144"}, {"id": "nema_gfx_lv_draw_nema_gfx_stm32_hal_nema_wait_irq_cl", "label": "nema_wait_irq_cl()", "file_type": "code", "source_file": "D:\\work\\datastore\\archives\\100ask_lvgl_docs\\src\\draw\\nema_gfx\\lv_draw_nema_gfx_stm32_hal.c", "source_location": "L150"}, {"id": "nema_gfx_lv_draw_nema_gfx_stm32_hal_nema_wait_irq_brk", "label": "nema_wait_irq_brk()", "file_type": "code", "source_file": "D:\\work\\datastore\\archives\\100ask_lvgl_docs\\src\\draw\\nema_gfx\\lv_draw_nema_gfx_stm32_hal.c", "source_location": "L159"}, {"id": "nema_gfx_lv_draw_nema_gfx_stm32_hal_nema_host_free", "label": "nema_host_free()", "file_type": "code", "source_file": "D:\\work\\datastore\\archives\\100ask_lvgl_docs\\src\\draw\\nema_gfx\\lv_draw_nema_gfx_stm32_hal.c", "source_location": "L168"}, {"id": "nema_gfx_lv_draw_nema_gfx_stm32_hal_nema_host_malloc", "label": "nema_host_malloc()", "file_type": "code", "source_file": "D:\\work\\datastore\\archives\\100ask_lvgl_docs\\src\\draw\\nema_gfx\\lv_draw_nema_gfx_stm32_hal.c", "source_location": "L173"}, {"id": "nema_gfx_lv_draw_nema_gfx_stm32_hal_nema_buffer_create", "label": "nema_buffer_create()", "file_type": "code", "source_file": "D:\\work\\datastore\\archives\\100ask_lvgl_docs\\src\\draw\\nema_gfx\\lv_draw_nema_gfx_stm32_hal.c", "source_location": "L178"}, {"id": "nema_gfx_lv_draw_nema_gfx_stm32_hal_nema_buffer_create_pool", "label": "nema_buffer_create_pool()", "file_type": "code", "source_file": "D:\\work\\datastore\\archives\\100ask_lvgl_docs\\src\\draw\\nema_gfx\\lv_draw_nema_gfx_stm32_hal.c", "source_location": "L190"}, {"id": "nema_gfx_lv_draw_nema_gfx_stm32_hal_nema_buffer_map", "label": "nema_buffer_map()", "file_type": "code", "source_file": "D:\\work\\datastore\\archives\\100ask_lvgl_docs\\src\\draw\\nema_gfx\\lv_draw_nema_gfx_stm32_hal.c", "source_location": "L197"}, {"id": "nema_gfx_lv_draw_nema_gfx_stm32_hal_nema_buffer_unmap", "label": "nema_buffer_unmap()", "file_type": "code", "source_file": "D:\\work\\datastore\\archives\\100ask_lvgl_docs\\src\\draw\\nema_gfx\\lv_draw_nema_gfx_stm32_hal.c", "source_location": "L202"}, {"id": "nema_gfx_lv_draw_nema_gfx_stm32_hal_nema_buffer_destroy", "label": "nema_buffer_destroy()", "file_type": "code", "source_file": "D:\\work\\datastore\\archives\\100ask_lvgl_docs\\src\\draw\\nema_gfx\\lv_draw_nema_gfx_stm32_hal.c", "source_location": "L207"}, {"id": "nema_gfx_lv_draw_nema_gfx_stm32_hal_nema_buffer_phys", "label": "nema_buffer_phys()", "file_type": "code", "source_file": "D:\\work\\datastore\\archives\\100ask_lvgl_docs\\src\\draw\\nema_gfx\\lv_draw_nema_gfx_stm32_hal.c", "source_location": "L221"}, {"id": "nema_gfx_lv_draw_nema_gfx_stm32_hal_nema_buffer_flush", "label": "nema_buffer_flush()", "file_type": "code", "source_file": "D:\\work\\datastore\\archives\\100ask_lvgl_docs\\src\\draw\\nema_gfx\\lv_draw_nema_gfx_stm32_hal.c", "source_location": "L226"}, {"id": "nema_gfx_lv_draw_nema_gfx_stm32_hal_nema_mutex_lock", "label": "nema_mutex_lock()", "file_type": "code", "source_file": "D:\\work\\datastore\\archives\\100ask_lvgl_docs\\src\\draw\\nema_gfx\\lv_draw_nema_gfx_stm32_hal.c", "source_location": "L231"}, {"id": "nema_gfx_lv_draw_nema_gfx_stm32_hal_nema_mutex_unlock", "label": "nema_mutex_unlock()", "file_type": "code", "source_file": "D:\\work\\datastore\\archives\\100ask_lvgl_docs\\src\\draw\\nema_gfx\\lv_draw_nema_gfx_stm32_hal.c", "source_location": "L240"}, {"id": "nema_gfx_lv_draw_nema_gfx_stm32_hal_platform_disable_cache", "label": "platform_disable_cache()", "file_type": "code", "source_file": "D:\\work\\datastore\\archives\\100ask_lvgl_docs\\src\\draw\\nema_gfx\\lv_draw_nema_gfx_stm32_hal.c", "source_location": "L249"}, {"id": "nema_gfx_lv_draw_nema_gfx_stm32_hal_platform_invalidate_cache", "label": "platform_invalidate_cache()", "file_type": "code", "source_file": "D:\\work\\datastore\\archives\\100ask_lvgl_docs\\src\\draw\\nema_gfx\\lv_draw_nema_gfx_stm32_hal.c", "source_location": "L254"}], "edges": [{"source": "d_work_datastore_archives_100ask_lvgl_docs_src_draw_nema_gfx_lv_draw_nema_gfx_stm32_hal_c", "target": "lv_conf_internal", "relation": "imports", "confidence": "EXTRACTED", "source_file": "D:\\work\\datastore\\archives\\100ask_lvgl_docs\\src\\draw\\nema_gfx\\lv_draw_nema_gfx_stm32_hal.c", "source_location": "L12", "weight": 1.0}, {"source": "d_work_datastore_archives_100ask_lvgl_docs_src_draw_nema_gfx_lv_draw_nema_gfx_stm32_hal_c", "target": "lv_types", "relation": "imports", "confidence": "EXTRACTED", "source_file": "D:\\work\\datastore\\archives\\100ask_lvgl_docs\\src\\draw\\nema_gfx\\lv_draw_nema_gfx_stm32_hal.c", "source_location": "L17", "weight": 1.0}, {"source": "d_work_datastore_archives_100ask_lvgl_docs_src_draw_nema_gfx_lv_draw_nema_gfx_stm32_hal_c", "target": "lv_assert", "relation": "imports", "confidence": "EXTRACTED", "source_file": "D:\\work\\datastore\\archives\\100ask_lvgl_docs\\src\\draw\\nema_gfx\\lv_draw_nema_gfx_stm32_hal.c", "source_location": "L18", "weight": 1.0}, {"source": "d_work_datastore_archives_100ask_lvgl_docs_src_draw_nema_gfx_lv_draw_nema_gfx_stm32_hal_c", "target": "lv_string", "relation": "imports", "confidence": "EXTRACTED", "source_file": "D:\\work\\datastore\\archives\\100ask_lvgl_docs\\src\\draw\\nema_gfx\\lv_draw_nema_gfx_stm32_hal.c", "source_location": "L19", "weight": 1.0}, {"source": "d_work_datastore_archives_100ask_lvgl_docs_src_draw_nema_gfx_lv_draw_nema_gfx_stm32_hal_c", "target": "nema_sys_defs", "relation": "imports", "confidence": "EXTRACTED", "source_file": "D:\\work\\datastore\\archives\\100ask_lvgl_docs\\src\\draw\\nema_gfx\\lv_draw_nema_gfx_stm32_hal.c", "source_location": "L21", "weight": 1.0}, {"source": "d_work_datastore_archives_100ask_lvgl_docs_src_draw_nema_gfx_lv_draw_nema_gfx_stm32_hal_c", "target": "nema_core", "relation": "imports", "confidence": "EXTRACTED", "source_file": "D:\\work\\datastore\\archives\\100ask_lvgl_docs\\src\\draw\\nema_gfx\\lv_draw_nema_gfx_stm32_hal.c", "source_location": "L22", "weight": 1.0}, {"source": "d_work_datastore_archives_100ask_lvgl_docs_src_draw_nema_gfx_lv_draw_nema_gfx_stm32_hal_c", "target": "assert", "relation": "imports", "confidence": "EXTRACTED", "source_file": "D:\\work\\datastore\\archives\\100ask_lvgl_docs\\src\\draw\\nema_gfx\\lv_draw_nema_gfx_stm32_hal.c", "source_location": "L24", "weight": 1.0}, {"source": "d_work_datastore_archives_100ask_lvgl_docs_src_draw_nema_gfx_lv_draw_nema_gfx_stm32_hal_c", "target": "string", "relation": "imports", "confidence": "EXTRACTED", "source_file": "D:\\work\\datastore\\archives\\100ask_lvgl_docs\\src\\draw\\nema_gfx\\lv_draw_nema_gfx_stm32_hal.c", "source_location": "L25", "weight": 1.0}, {"source": "d_work_datastore_archives_100ask_lvgl_docs_src_draw_nema_gfx_lv_draw_nema_gfx_stm32_hal_c", "target": "cmsis_os2", "relation": "imports", "confidence": "EXTRACTED", "source_file": "D:\\work\\datastore\\archives\\100ask_lvgl_docs\\src\\draw\\nema_gfx\\lv_draw_nema_gfx_stm32_hal.c", "source_location": "L29", "weight": 1.0}, {"source": "d_work_datastore_archives_100ask_lvgl_docs_src_draw_nema_gfx_lv_draw_nema_gfx_stm32_hal_c", "target": "tsi_malloc", "relation": "imports", "confidence": "EXTRACTED", "source_file": "D:\\work\\datastore\\archives\\100ask_lvgl_docs\\src\\draw\\nema_gfx\\lv_draw_nema_gfx_stm32_hal.c", "source_location": "L31", "weight": 1.0}, {"source": "d_work_datastore_archives_100ask_lvgl_docs_src_draw_nema_gfx_lv_draw_nema_gfx_stm32_hal_c", "target": "nema_gfx_lv_draw_nema_gfx_stm32_hal_hal_gpu2d_commandlistcpltcallback", "relation": "contains", "confidence": "EXTRACTED", "source_file": "D:\\work\\datastore\\archives\\100ask_lvgl_docs\\src\\draw\\nema_gfx\\lv_draw_nema_gfx_stm32_hal.c", "source_location": "L85", "weight": 1.0}, {"source": "d_work_datastore_archives_100ask_lvgl_docs_src_draw_nema_gfx_lv_draw_nema_gfx_stm32_hal_c", "target": "nema_gfx_lv_draw_nema_gfx_stm32_hal_nema_sys_init", "relation": "contains", "confidence": "EXTRACTED", "source_file": "D:\\work\\datastore\\archives\\100ask_lvgl_docs\\src\\draw\\nema_gfx\\lv_draw_nema_gfx_stm32_hal.c", "source_location": "L96", "weight": 1.0}, {"source": "d_work_datastore_archives_100ask_lvgl_docs_src_draw_nema_gfx_lv_draw_nema_gfx_stm32_hal_c", "target": "nema_gfx_lv_draw_nema_gfx_stm32_hal_nema_reg_read", "relation": "contains", "confidence": "EXTRACTED", "source_file": "D:\\work\\datastore\\archives\\100ask_lvgl_docs\\src\\draw\\nema_gfx\\lv_draw_nema_gfx_stm32_hal.c", "source_location": "L131", "weight": 1.0}, {"source": "d_work_datastore_archives_100ask_lvgl_docs_src_draw_nema_gfx_lv_draw_nema_gfx_stm32_hal_c", "target": "nema_gfx_lv_draw_nema_gfx_stm32_hal_nema_reg_write", "relation": "contains", "confidence": "EXTRACTED", "source_file": "D:\\work\\datastore\\archives\\100ask_lvgl_docs\\src\\draw\\nema_gfx\\lv_draw_nema_gfx_stm32_hal.c", "source_location": "L136", "weight": 1.0}, {"source": "d_work_datastore_archives_100ask_lvgl_docs_src_draw_nema_gfx_lv_draw_nema_gfx_stm32_hal_c", "target": "nema_gfx_lv_draw_nema_gfx_stm32_hal_nema_wait_irq", "relation": "contains", "confidence": "EXTRACTED", "source_file": "D:\\work\\datastore\\archives\\100ask_lvgl_docs\\src\\draw\\nema_gfx\\lv_draw_nema_gfx_stm32_hal.c", "source_location": "L144", "weight": 1.0}, {"source": "d_work_datastore_archives_100ask_lvgl_docs_src_draw_nema_gfx_lv_draw_nema_gfx_stm32_hal_c", "target": "nema_gfx_lv_draw_nema_gfx_stm32_hal_nema_wait_irq_cl", "relation": "contains", "confidence": "EXTRACTED", "source_file": "D:\\work\\datastore\\archives\\100ask_lvgl_docs\\src\\draw\\nema_gfx\\lv_draw_nema_gfx_stm32_hal.c", "source_location": "L150", "weight": 1.0}, {"source": "d_work_datastore_archives_100ask_lvgl_docs_src_draw_nema_gfx_lv_draw_nema_gfx_stm32_hal_c", "target": "nema_gfx_lv_draw_nema_gfx_stm32_hal_nema_wait_irq_brk", "relation": "contains", "confidence": "EXTRACTED", "source_file": "D:\\work\\datastore\\archives\\100ask_lvgl_docs\\src\\draw\\nema_gfx\\lv_draw_nema_gfx_stm32_hal.c", "source_location": "L159", "weight": 1.0}, {"source": "d_work_datastore_archives_100ask_lvgl_docs_src_draw_nema_gfx_lv_draw_nema_gfx_stm32_hal_c", "target": "nema_gfx_lv_draw_nema_gfx_stm32_hal_nema_host_free", "relation": "contains", "confidence": "EXTRACTED", "source_file": "D:\\work\\datastore\\archives\\100ask_lvgl_docs\\src\\draw\\nema_gfx\\lv_draw_nema_gfx_stm32_hal.c", "source_location": "L168", "weight": 1.0}, {"source": "d_work_datastore_archives_100ask_lvgl_docs_src_draw_nema_gfx_lv_draw_nema_gfx_stm32_hal_c", "target": "nema_gfx_lv_draw_nema_gfx_stm32_hal_nema_host_malloc", "relation": "contains", "confidence": "EXTRACTED", "source_file": "D:\\work\\datastore\\archives\\100ask_lvgl_docs\\src\\draw\\nema_gfx\\lv_draw_nema_gfx_stm32_hal.c", "source_location": "L173", "weight": 1.0}, {"source": "d_work_datastore_archives_100ask_lvgl_docs_src_draw_nema_gfx_lv_draw_nema_gfx_stm32_hal_c", "target": "nema_gfx_lv_draw_nema_gfx_stm32_hal_nema_buffer_create", "relation": "contains", "confidence": "EXTRACTED", "source_file": "D:\\work\\datastore\\archives\\100ask_lvgl_docs\\src\\draw\\nema_gfx\\lv_draw_nema_gfx_stm32_hal.c", "source_location": "L178", "weight": 1.0}, {"source": "d_work_datastore_archives_100ask_lvgl_docs_src_draw_nema_gfx_lv_draw_nema_gfx_stm32_hal_c", "target": "nema_gfx_lv_draw_nema_gfx_stm32_hal_nema_buffer_create_pool", "relation": "contains", "confidence": "EXTRACTED", "source_file": "D:\\work\\datastore\\archives\\100ask_lvgl_docs\\src\\draw\\nema_gfx\\lv_draw_nema_gfx_stm32_hal.c", "source_location": "L190", "weight": 1.0}, {"source": "d_work_datastore_archives_100ask_lvgl_docs_src_draw_nema_gfx_lv_draw_nema_gfx_stm32_hal_c", "target": "nema_gfx_lv_draw_nema_gfx_stm32_hal_nema_buffer_map", "relation": "contains", "confidence": "EXTRACTED", "source_file": "D:\\work\\datastore\\archives\\100ask_lvgl_docs\\src\\draw\\nema_gfx\\lv_draw_nema_gfx_stm32_hal.c", "source_location": "L197", "weight": 1.0}, {"source": "d_work_datastore_archives_100ask_lvgl_docs_src_draw_nema_gfx_lv_draw_nema_gfx_stm32_hal_c", "target": "nema_gfx_lv_draw_nema_gfx_stm32_hal_nema_buffer_unmap", "relation": "contains", "confidence": "EXTRACTED", "source_file": "D:\\work\\datastore\\archives\\100ask_lvgl_docs\\src\\draw\\nema_gfx\\lv_draw_nema_gfx_stm32_hal.c", "source_location": "L202", "weight": 1.0}, {"source": "d_work_datastore_archives_100ask_lvgl_docs_src_draw_nema_gfx_lv_draw_nema_gfx_stm32_hal_c", "target": "nema_gfx_lv_draw_nema_gfx_stm32_hal_nema_buffer_destroy", "relation": "contains", "confidence": "EXTRACTED", "source_file": "D:\\work\\datastore\\archives\\100ask_lvgl_docs\\src\\draw\\nema_gfx\\lv_draw_nema_gfx_stm32_hal.c", "source_location": "L207", "weight": 1.0}, {"source": "d_work_datastore_archives_100ask_lvgl_docs_src_draw_nema_gfx_lv_draw_nema_gfx_stm32_hal_c", "target": "nema_gfx_lv_draw_nema_gfx_stm32_hal_nema_buffer_phys", "relation": "contains", "confidence": "EXTRACTED", "source_file": "D:\\work\\datastore\\archives\\100ask_lvgl_docs\\src\\draw\\nema_gfx\\lv_draw_nema_gfx_stm32_hal.c", "source_location": "L221", "weight": 1.0}, {"source": "d_work_datastore_archives_100ask_lvgl_docs_src_draw_nema_gfx_lv_draw_nema_gfx_stm32_hal_c", "target": "nema_gfx_lv_draw_nema_gfx_stm32_hal_nema_buffer_flush", "relation": "contains", "confidence": "EXTRACTED", "source_file": "D:\\work\\datastore\\archives\\100ask_lvgl_docs\\src\\draw\\nema_gfx\\lv_draw_nema_gfx_stm32_hal.c", "source_location": "L226", "weight": 1.0}, {"source": "d_work_datastore_archives_100ask_lvgl_docs_src_draw_nema_gfx_lv_draw_nema_gfx_stm32_hal_c", "target": "nema_gfx_lv_draw_nema_gfx_stm32_hal_nema_mutex_lock", "relation": "contains", "confidence": "EXTRACTED", "source_file": "D:\\work\\datastore\\archives\\100ask_lvgl_docs\\src\\draw\\nema_gfx\\lv_draw_nema_gfx_stm32_hal.c", "source_location": "L231", "weight": 1.0}, {"source": "d_work_datastore_archives_100ask_lvgl_docs_src_draw_nema_gfx_lv_draw_nema_gfx_stm32_hal_c", "target": "nema_gfx_lv_draw_nema_gfx_stm32_hal_nema_mutex_unlock", "relation": "contains", "confidence": "EXTRACTED", "source_file": "D:\\work\\datastore\\archives\\100ask_lvgl_docs\\src\\draw\\nema_gfx\\lv_draw_nema_gfx_stm32_hal.c", "source_location": "L240", "weight": 1.0}, {"source": "d_work_datastore_archives_100ask_lvgl_docs_src_draw_nema_gfx_lv_draw_nema_gfx_stm32_hal_c", "target": "nema_gfx_lv_draw_nema_gfx_stm32_hal_platform_disable_cache", "relation": "contains", "confidence": "EXTRACTED", "source_file": "D:\\work\\datastore\\archives\\100ask_lvgl_docs\\src\\draw\\nema_gfx\\lv_draw_nema_gfx_stm32_hal.c", "source_location": "L249", "weight": 1.0}, {"source": "d_work_datastore_archives_100ask_lvgl_docs_src_draw_nema_gfx_lv_draw_nema_gfx_stm32_hal_c", "target": "nema_gfx_lv_draw_nema_gfx_stm32_hal_platform_invalidate_cache", "relation": "contains", "confidence": "EXTRACTED", "source_file": "D:\\work\\datastore\\archives\\100ask_lvgl_docs\\src\\draw\\nema_gfx\\lv_draw_nema_gfx_stm32_hal.c", "source_location": "L254", "weight": 1.0}, {"source": "nema_gfx_lv_draw_nema_gfx_stm32_hal_nema_sys_init", "target": "nema_gfx_lv_draw_nema_gfx_stm32_hal_nema_buffer_create", "relation": "calls", "confidence": "EXTRACTED", "source_file": "D:\\work\\datastore\\archives\\100ask_lvgl_docs\\src\\draw\\nema_gfx\\lv_draw_nema_gfx_stm32_hal.c", "source_location": "L116", "weight": 1.0}, {"source": "nema_gfx_lv_draw_nema_gfx_stm32_hal_nema_wait_irq_cl", "target": "nema_gfx_lv_draw_nema_gfx_stm32_hal_nema_wait_irq", "relation": "calls", "confidence": "EXTRACTED", "source_file": "D:\\work\\datastore\\archives\\100ask_lvgl_docs\\src\\draw\\nema_gfx\\lv_draw_nema_gfx_stm32_hal.c", "source_location": "L153", "weight": 1.0}, {"source": "nema_gfx_lv_draw_nema_gfx_stm32_hal_nema_wait_irq_brk", "target": "nema_gfx_lv_draw_nema_gfx_stm32_hal_nema_reg_read", "relation": "calls", "confidence": "EXTRACTED", "source_file": "D:\\work\\datastore\\archives\\100ask_lvgl_docs\\src\\draw\\nema_gfx\\lv_draw_nema_gfx_stm32_hal.c", "source_location": "L161", "weight": 1.0}, {"source": "nema_gfx_lv_draw_nema_gfx_stm32_hal_nema_wait_irq_brk", "target": "nema_gfx_lv_draw_nema_gfx_stm32_hal_nema_wait_irq", "relation": "calls", "confidence": "EXTRACTED", "source_file": "D:\\work\\datastore\\archives\\100ask_lvgl_docs\\src\\draw\\nema_gfx\\lv_draw_nema_gfx_stm32_hal.c", "source_location": "L162", "weight": 1.0}, {"source": "nema_gfx_lv_draw_nema_gfx_stm32_hal_nema_buffer_create_pool", "target": "nema_gfx_lv_draw_nema_gfx_stm32_hal_nema_buffer_create", "relation": "calls", "confidence": "EXTRACTED", "source_file": "D:\\work\\datastore\\archives\\100ask_lvgl_docs\\src\\draw\\nema_gfx\\lv_draw_nema_gfx_stm32_hal.c", "source_location": "L194", "weight": 1.0}], "raw_calls": [{"caller_nid": "nema_gfx_lv_draw_nema_gfx_stm32_hal_hal_gpu2d_commandlistcpltcallback", "callee": "LV_UNUSED", "is_member_call": false, "source_file": "D:\\work\\datastore\\archives\\100ask_lvgl_docs\\src\\draw\\nema_gfx\\lv_draw_nema_gfx_stm32_hal.c", "source_location": "L88"}, {"caller_nid": "nema_gfx_lv_draw_nema_gfx_stm32_hal_nema_sys_init", "callee": "HAL_GPU2D_RegisterCommandListCpltCallback", "is_member_call": false, "source_file": "D:\\work\\datastore\\archives\\100ask_lvgl_docs\\src\\draw\\nema_gfx\\lv_draw_nema_gfx_stm32_hal.c", "source_location": "L103"}, {"caller_nid": "nema_gfx_lv_draw_nema_gfx_stm32_hal_nema_sys_init", "callee": "tsi_malloc_init_pool_aligned", "is_member_call": false, "source_file": "D:\\work\\datastore\\archives\\100ask_lvgl_docs\\src\\draw\\nema_gfx\\lv_draw_nema_gfx_stm32_hal.c", "source_location": "L111"}, {"caller_nid": "nema_gfx_lv_draw_nema_gfx_stm32_hal_nema_sys_init", "callee": "LV_ASSERT", "is_member_call": false, "source_file": "D:\\work\\datastore\\archives\\100ask_lvgl_docs\\src\\draw\\nema_gfx\\lv_draw_nema_gfx_stm32_hal.c", "source_location": "L113"}, {"caller_nid": "nema_gfx_lv_draw_nema_gfx_stm32_hal_nema_sys_init", "callee": "LV_ASSERT", "is_member_call": false, "source_file": "D:\\work\\datastore\\archives\\100ask_lvgl_docs\\src\\draw\\nema_gfx\\lv_draw_nema_gfx_stm32_hal.c", "source_location": "L117"}, {"caller_nid": "nema_gfx_lv_draw_nema_gfx_stm32_hal_nema_sys_init", "callee": "nema_rb_init", "is_member_call": false, "source_file": "D:\\work\\datastore\\archives\\100ask_lvgl_docs\\src\\draw\\nema_gfx\\lv_draw_nema_gfx_stm32_hal.c", "source_location": "L120"}, {"caller_nid": "nema_gfx_lv_draw_nema_gfx_stm32_hal_nema_reg_read", "callee": "HAL_GPU2D_ReadRegister", "is_member_call": false, "source_file": "D:\\work\\datastore\\archives\\100ask_lvgl_docs\\src\\draw\\nema_gfx\\lv_draw_nema_gfx_stm32_hal.c", "source_location": "L133"}, {"caller_nid": "nema_gfx_lv_draw_nema_gfx_stm32_hal_nema_reg_write", "callee": "HAL_GPU2D_WriteRegister", "is_member_call": false, "source_file": "D:\\work\\datastore\\archives\\100ask_lvgl_docs\\src\\draw\\nema_gfx\\lv_draw_nema_gfx_stm32_hal.c", "source_location": "L138"}, {"caller_nid": "nema_gfx_lv_draw_nema_gfx_stm32_hal_nema_host_free", "callee": "tsi_free", "is_member_call": false, "source_file": "D:\\work\\datastore\\archives\\100ask_lvgl_docs\\src\\draw\\nema_gfx\\lv_draw_nema_gfx_stm32_hal.c", "source_location": "L170"}, {"caller_nid": "nema_gfx_lv_draw_nema_gfx_stm32_hal_nema_host_malloc", "callee": "tsi_malloc", "is_member_call": false, "source_file": "D:\\work\\datastore\\archives\\100ask_lvgl_docs\\src\\draw\\nema_gfx\\lv_draw_nema_gfx_stm32_hal.c", "source_location": "L175"}, {"caller_nid": "nema_gfx_lv_draw_nema_gfx_stm32_hal_nema_buffer_create", "callee": "lv_memset", "is_member_call": false, "source_file": "D:\\work\\datastore\\archives\\100ask_lvgl_docs\\src\\draw\\nema_gfx\\lv_draw_nema_gfx_stm32_hal.c", "source_location": "L181"}, {"caller_nid": "nema_gfx_lv_draw_nema_gfx_stm32_hal_nema_buffer_create", "callee": "tsi_malloc", "is_member_call": false, "source_file": "D:\\work\\datastore\\archives\\100ask_lvgl_docs\\src\\draw\\nema_gfx\\lv_draw_nema_gfx_stm32_hal.c", "source_location": "L182"}, {"caller_nid": "nema_gfx_lv_draw_nema_gfx_stm32_hal_nema_buffer_create", "callee": "LV_ASSERT_MSG", "is_member_call": false, "source_file": "D:\\work\\datastore\\archives\\100ask_lvgl_docs\\src\\draw\\nema_gfx\\lv_draw_nema_gfx_stm32_hal.c", "source_location": "L185"}, {"caller_nid": "nema_gfx_lv_draw_nema_gfx_stm32_hal_nema_buffer_create_pool", "callee": "LV_UNUSED", "is_member_call": false, "source_file": "D:\\work\\datastore\\archives\\100ask_lvgl_docs\\src\\draw\\nema_gfx\\lv_draw_nema_gfx_stm32_hal.c", "source_location": "L192"}, {"caller_nid": "nema_gfx_lv_draw_nema_gfx_stm32_hal_nema_buffer_unmap", "callee": "LV_UNUSED", "is_member_call": false, "source_file": "D:\\work\\datastore\\archives\\100ask_lvgl_docs\\src\\draw\\nema_gfx\\lv_draw_nema_gfx_stm32_hal.c", "source_location": "L204"}, {"caller_nid": "nema_gfx_lv_draw_nema_gfx_stm32_hal_nema_buffer_destroy", "callee": "tsi_free", "is_member_call": false, "source_file": "D:\\work\\datastore\\archives\\100ask_lvgl_docs\\src\\draw\\nema_gfx\\lv_draw_nema_gfx_stm32_hal.c", "source_location": "L213"}, {"caller_nid": "nema_gfx_lv_draw_nema_gfx_stm32_hal_nema_buffer_flush", "callee": "LV_UNUSED", "is_member_call": false, "source_file": "D:\\work\\datastore\\archives\\100ask_lvgl_docs\\src\\draw\\nema_gfx\\lv_draw_nema_gfx_stm32_hal.c", "source_location": "L228"}, {"caller_nid": "nema_gfx_lv_draw_nema_gfx_stm32_hal_nema_mutex_lock", "callee": "LV_UNUSED", "is_member_call": false, "source_file": "D:\\work\\datastore\\archives\\100ask_lvgl_docs\\src\\draw\\nema_gfx\\lv_draw_nema_gfx_stm32_hal.c", "source_location": "L235"}, {"caller_nid": "nema_gfx_lv_draw_nema_gfx_stm32_hal_nema_mutex_unlock", "callee": "LV_UNUSED", "is_member_call": false, "source_file": "D:\\work\\datastore\\archives\\100ask_lvgl_docs\\src\\draw\\nema_gfx\\lv_draw_nema_gfx_stm32_hal.c", "source_location": "L244"}]}