{"nodes": [{"id": "apps_api_tests_api_conftest_py", "label": "conftest.py", "file_type": "code", "source_file": "apps\\api\\tests\\api\\conftest.py", "source_location": "L1"}, {"id": "conftest_event_loop", "label": "event_loop()", "file_type": "code", "source_file": "apps\\api\\tests\\api\\conftest.py", "source_location": "L26"}, {"id": "conftest_test_db_name", "label": "test_db_name()", "file_type": "code", "source_file": "apps\\api\\tests\\api\\conftest.py", "source_location": "L33"}, {"id": "conftest_mongo_client", "label": "mongo_client()", "file_type": "code", "source_file": "apps\\api\\tests\\api\\conftest.py", "source_location": "L38"}, {"id": "conftest_test_db", "label": "test_db()", "file_type": "code", "source_file": "apps\\api\\tests\\api\\conftest.py", "source_location": "L54"}, {"id": "conftest_app", "label": "app()", "file_type": "code", "source_file": "apps\\api\\tests\\api\\conftest.py", "source_location": "L60"}, {"id": "conftest_async_client", "label": "async_client()", "file_type": "code", "source_file": "apps\\api\\tests\\api\\conftest.py", "source_location": "L67"}, {"id": "conftest_sync_client", "label": "sync_client()", "file_type": "code", "source_file": "apps\\api\\tests\\api\\conftest.py", "source_location": "L75"}, {"id": "conftest_test_user_data", "label": "test_user_data()", "file_type": "code", "source_file": "apps\\api\\tests\\api\\conftest.py", "source_location": "L81"}, {"id": "conftest_test_admin_data", "label": "test_admin_data()", "file_type": "code", "source_file": "apps\\api\\tests\\api\\conftest.py", "source_location": "L92"}, {"id": "conftest_test_role_data", "label": "test_role_data()", "file_type": "code", "source_file": "apps\\api\\tests\\api\\conftest.py", "source_location": "L104"}, {"id": "conftest_setup_test_db", "label": "setup_test_db()", "file_type": "code", "source_file": "apps\\api\\tests\\api\\conftest.py", "source_location": "L114"}, {"id": "conftest_auth_headers", "label": "auth_headers()", "file_type": "code", "source_file": "apps\\api\\tests\\api\\conftest.py", "source_location": "L173"}, {"id": "conftest_viewer_auth_headers", "label": "viewer_auth_headers()", "file_type": "code", "source_file": "apps\\api\\tests\\api\\conftest.py", "source_location": "L189"}, {"id": "conftest_trader_auth_headers", "label": "trader_auth_headers()", "file_type": "code", "source_file": "apps\\api\\tests\\api\\conftest.py", "source_location": "L215"}], "edges": [{"source": "apps_api_tests_api_conftest_py", "target": "asyncio", "relation": "imports", "confidence": "EXTRACTED", "source_file": "apps\\api\\tests\\api\\conftest.py", "source_location": "L1", "weight": 1.0}, {"source": "apps_api_tests_api_conftest_py", "target": "os", "relation": "imports", "confidence": "EXTRACTED", "source_file": "apps\\api\\tests\\api\\conftest.py", "source_location": "L2", "weight": 1.0}, {"source": "apps_api_tests_api_conftest_py", "target": "uuid", "relation": "imports", "confidence": "EXTRACTED", "source_file": "apps\\api\\tests\\api\\conftest.py", "source_location": "L3", "weight": 1.0}, {"source": "apps_api_tests_api_conftest_py", "target": "datetime", "relation": "imports_from", "confidence": "EXTRACTED", "source_file": "apps\\api\\tests\\api\\conftest.py", "source_location": "L4", "weight": 1.0}, {"source": "apps_api_tests_api_conftest_py", "target": "typing", "relation": "imports_from", "confidence": "EXTRACTED", "source_file": "apps\\api\\tests\\api\\conftest.py", "source_location": "L5", "weight": 1.0}, {"source": "apps_api_tests_api_conftest_py", "target": "unittest_mock", "relation": "imports_from", "confidence": "EXTRACTED", "source_file": "apps\\api\\tests\\api\\conftest.py", "source_location": "L6", "weight": 1.0}, {"source": "apps_api_tests_api_conftest_py", "target": "pytest", "relation": "imports", "confidence": "EXTRACTED", "source_file": "apps\\api\\tests\\api\\conftest.py", "source_location": "L8", "weight": 1.0}, {"source": "apps_api_tests_api_conftest_py", "target": "pytest_asyncio", "relation": "imports", "confidence": "EXTRACTED", "source_file": "apps\\api\\tests\\api\\conftest.py", "source_location": "L9", "weight": 1.0}, {"source": "apps_api_tests_api_conftest_py", "target": "fastapi_testclient", "relation": "imports_from", "confidence": "EXTRACTED", "source_file": "apps\\api\\tests\\api\\conftest.py", "source_location": "L10", "weight": 1.0}, {"source": "apps_api_tests_api_conftest_py", "target": "httpx", "relation": "imports_from", "confidence": "EXTRACTED", "source_file": "apps\\api\\tests\\api\\conftest.py", "source_location": "L11", "weight": 1.0}, {"source": "apps_api_tests_api_conftest_py", "target": "pymongo", "relation": "imports_from", "confidence": "EXTRACTED", "source_file": "apps\\api\\tests\\api\\conftest.py", "source_location": "L12", "weight": 1.0}, {"source": "apps_api_tests_api_conftest_py", "target": "pymongo_errors", "relation": "imports_from", "confidence": "EXTRACTED", "source_file": "apps\\api\\tests\\api\\conftest.py", "source_location": "L13", "weight": 1.0}, {"source": "apps_api_tests_api_conftest_py", "target": "sys", "relation": "imports", "confidence": "EXTRACTED", "source_file": "apps\\api\\tests\\api\\conftest.py", "source_location": "L15", "weight": 1.0}, {"source": "apps_api_tests_api_conftest_py", "target": "app_core_config", "relation": "imports_from", "confidence": "EXTRACTED", "source_file": "apps\\api\\tests\\api\\conftest.py", "source_location": "L21", "weight": 1.0}, {"source": "apps_api_tests_api_conftest_py", "target": "app_user_password", "relation": "imports_from", "confidence": "EXTRACTED", "source_file": "apps\\api\\tests\\api\\conftest.py", "source_location": "L22", "weight": 1.0}, {"source": "apps_api_tests_api_conftest_py", "target": "conftest_event_loop", "relation": "contains", "confidence": "EXTRACTED", "source_file": "apps\\api\\tests\\api\\conftest.py", "source_location": "L26", "weight": 1.0}, {"source": "apps_api_tests_api_conftest_py", "target": "conftest_test_db_name", "relation": "contains", "confidence": "EXTRACTED", "source_file": "apps\\api\\tests\\api\\conftest.py", "source_location": "L33", "weight": 1.0}, {"source": "apps_api_tests_api_conftest_py", "target": "conftest_mongo_client", "relation": "contains", "confidence": "EXTRACTED", "source_file": "apps\\api\\tests\\api\\conftest.py", "source_location": "L38", "weight": 1.0}, {"source": "apps_api_tests_api_conftest_py", "target": "conftest_test_db", "relation": "contains", "confidence": "EXTRACTED", "source_file": "apps\\api\\tests\\api\\conftest.py", "source_location": "L54", "weight": 1.0}, {"source": "apps_api_tests_api_conftest_py", "target": "conftest_app", "relation": "contains", "confidence": "EXTRACTED", "source_file": "apps\\api\\tests\\api\\conftest.py", "source_location": "L60", "weight": 1.0}, {"source": "apps_api_tests_api_conftest_py", "target": "conftest_async_client", "relation": "contains", "confidence": "EXTRACTED", "source_file": "apps\\api\\tests\\api\\conftest.py", "source_location": "L67", "weight": 1.0}, {"source": "apps_api_tests_api_conftest_py", "target": "conftest_sync_client", "relation": "contains", "confidence": "EXTRACTED", "source_file": "apps\\api\\tests\\api\\conftest.py", "source_location": "L75", "weight": 1.0}, {"source": "apps_api_tests_api_conftest_py", "target": "conftest_test_user_data", "relation": "contains", "confidence": "EXTRACTED", "source_file": "apps\\api\\tests\\api\\conftest.py", "source_location": "L81", "weight": 1.0}, {"source": "apps_api_tests_api_conftest_py", "target": "conftest_test_admin_data", "relation": "contains", "confidence": "EXTRACTED", "source_file": "apps\\api\\tests\\api\\conftest.py", "source_location": "L92", "weight": 1.0}, {"source": "apps_api_tests_api_conftest_py", "target": "conftest_test_role_data", "relation": "contains", "confidence": "EXTRACTED", "source_file": "apps\\api\\tests\\api\\conftest.py", "source_location": "L104", "weight": 1.0}, {"source": "apps_api_tests_api_conftest_py", "target": "conftest_setup_test_db", "relation": "contains", "confidence": "EXTRACTED", "source_file": "apps\\api\\tests\\api\\conftest.py", "source_location": "L114", "weight": 1.0}, {"source": "apps_api_tests_api_conftest_py", "target": "conftest_auth_headers", "relation": "contains", "confidence": "EXTRACTED", "source_file": "apps\\api\\tests\\api\\conftest.py", "source_location": "L173", "weight": 1.0}, {"source": "apps_api_tests_api_conftest_py", "target": "conftest_viewer_auth_headers", "relation": "contains", "confidence": "EXTRACTED", "source_file": "apps\\api\\tests\\api\\conftest.py", "source_location": "L189", "weight": 1.0}, {"source": "apps_api_tests_api_conftest_py", "target": "conftest_trader_auth_headers", "relation": "contains", "confidence": "EXTRACTED", "source_file": "apps\\api\\tests\\api\\conftest.py", "source_location": "L215", "weight": 1.0}], "raw_calls": [{"caller_nid": "conftest_event_loop", "callee": "new_event_loop", "source_file": "apps\\api\\tests\\api\\conftest.py", "source_location": "L27"}, {"caller_nid": "conftest_event_loop", "callee": "get_event_loop_policy", "source_file": "apps\\api\\tests\\api\\conftest.py", "source_location": "L27"}, {"caller_nid": "conftest_event_loop", "callee": "close", "source_file": "apps\\api\\tests\\api\\conftest.py", "source_location": "L29"}, {"caller_nid": "conftest_test_db_name", "callee": "uuid4", "source_file": "apps\\api\\tests\\api\\conftest.py", "source_location": "L34"}, {"caller_nid": "conftest_mongo_client", "callee": "MongoClient", "source_file": "apps\\api\\tests\\api\\conftest.py", "source_location": "L39"}, {"caller_nid": "conftest_mongo_client", "callee": "drop_database", "source_file": "apps\\api\\tests\\api\\conftest.py", "source_location": "L47"}, {"caller_nid": "conftest_mongo_client", "callee": "close", "source_file": "apps\\api\\tests\\api\\conftest.py", "source_location": "L50"}, {"caller_nid": "conftest_async_client", "callee": "AsyncClient", "source_file": "apps\\api\\tests\\api\\conftest.py", "source_location": "L68"}, {"caller_nid": "conftest_async_client", "callee": "ASGITransport", "source_file": "apps\\api\\tests\\api\\conftest.py", "source_location": "L69"}, {"caller_nid": "conftest_sync_client", "callee": "TestClient", "source_file": "apps\\api\\tests\\api\\conftest.py", "source_location": "L76"}, {"caller_nid": "conftest_setup_test_db", "callee": "isoformat", "source_file": "apps\\api\\tests\\api\\conftest.py", "source_location": "L120"}, {"caller_nid": "conftest_setup_test_db", "callee": "now", "source_file": "apps\\api\\tests\\api\\conftest.py", "source_location": "L120"}, {"caller_nid": "conftest_setup_test_db", "callee": "isoformat", "source_file": "apps\\api\\tests\\api\\conftest.py", "source_location": "L121"}, {"caller_nid": "conftest_setup_test_db", "callee": "now", "source_file": "apps\\api\\tests\\api\\conftest.py", "source_location": "L121"}, {"caller_nid": "conftest_setup_test_db", "callee": "update_one", "source_file": "apps\\api\\tests\\api\\conftest.py", "source_location": "L122"}, {"caller_nid": "conftest_setup_test_db", "callee": "isoformat", "source_file": "apps\\api\\tests\\api\\conftest.py", "source_location": "L124"}, {"caller_nid": "conftest_setup_test_db", "callee": "now", "source_file": "apps\\api\\tests\\api\\conftest.py", "source_location": "L124"}, {"caller_nid": "conftest_setup_test_db", "callee": "isoformat", "source_file": "apps\\api\\tests\\api\\conftest.py", "source_location": "L125"}, {"caller_nid": "conftest_setup_test_db", "callee": "now", "source_file": "apps\\api\\tests\\api\\conftest.py", "source_location": "L125"}, {"caller_nid": "conftest_setup_test_db", "callee": "update_one", "source_file": "apps\\api\\tests\\api\\conftest.py", "source_location": "L127"}, {"caller_nid": "conftest_setup_test_db", "callee": "now", "source_file": "apps\\api\\tests\\api\\conftest.py", "source_location": "L133"}, {"caller_nid": "conftest_setup_test_db", "callee": "hash_password", "source_file": "apps\\api\\tests\\api\\conftest.py", "source_location": "L136"}, {"caller_nid": "conftest_setup_test_db", "callee": "get", "source_file": "apps\\api\\tests\\api\\conftest.py", "source_location": "L140"}, {"caller_nid": "conftest_setup_test_db", "callee": "isoformat", "source_file": "apps\\api\\tests\\api\\conftest.py", "source_location": "L141"}, {"caller_nid": "conftest_setup_test_db", "callee": "isoformat", "source_file": "apps\\api\\tests\\api\\conftest.py", "source_location": "L142"}, {"caller_nid": "conftest_setup_test_db", "callee": "update_one", "source_file": "apps\\api\\tests\\api\\conftest.py", "source_location": "L145"}, {"caller_nid": "conftest_setup_test_db", "callee": "hash_password", "source_file": "apps\\api\\tests\\api\\conftest.py", "source_location": "L151"}, {"caller_nid": "conftest_setup_test_db", "callee": "isoformat", "source_file": "apps\\api\\tests\\api\\conftest.py", "source_location": "L156"}, {"caller_nid": "conftest_setup_test_db", "callee": "isoformat", "source_file": "apps\\api\\tests\\api\\conftest.py", "source_location": "L157"}, {"caller_nid": "conftest_setup_test_db", "callee": "update_one", "source_file": "apps\\api\\tests\\api\\conftest.py", "source_location": "L160"}, {"caller_nid": "conftest_setup_test_db", "callee": "delete_many", "source_file": "apps\\api\\tests\\api\\conftest.py", "source_location": "L166"}, {"caller_nid": "conftest_setup_test_db", "callee": "delete_many", "source_file": "apps\\api\\tests\\api\\conftest.py", "source_location": "L169"}, {"caller_nid": "conftest_auth_headers", "callee": "create_access_token", "source_file": "apps\\api\\tests\\api\\conftest.py", "source_location": "L176"}, {"caller_nid": "conftest_viewer_auth_headers", "callee": "create_access_token", "source_file": "apps\\api\\tests\\api\\conftest.py", "source_location": "L192"}, {"caller_nid": "conftest_trader_auth_headers", "callee": "create_access_token", "source_file": "apps\\api\\tests\\api\\conftest.py", "source_location": "L218"}]}